py2http/__init__.py
py2http/bottle_plugins.py
py2http/config.py
py2http/constants.py
py2http/decorators.py
py2http/default_configs.py
py2http/diagnosis.py
py2http/middleware.py
py2http/openapi_utils.py
py2http/route_utils.py
py2http/schema_tools.py
py2http/service.py
py2http/types.py
py2http/util.py
py2http/examples/__init__.py
py2http/examples/custom_input_mapper.py
py2http/examples/custom_input_mappers.py
py2http/examples/example_service.py
py2http/examples/example_service_bottle.py
py2http/examples/example_service_flask.py
py2http/examples/object_dispatch.py
py2http/tests/__init__.py
py2http/tests/example_service_test.py
py2http/tests/objects_for_testing.py
py2http/tests/simple_run_process_test.py
py2http/tests/test_decorators.py
py2http/tests/test_flask.py
py2http/tests/test_p2h2p.py
py2http/tests/utils_for_testing.py
py2http-0.1.60.dist-info/LICENSE
py2http-0.1.60.dist-info/METADATA
py2http-0.1.60.dist-info/WHEEL
py2http-0.1.60.dist-info/top_level.txt
py2http-0.1.60.dist-info/RECORD
