Metadata-Version: 2.1
Name: py2http
Version: 0.1.60
Summary: Declarative HTTP service entry point.
Home-page: https://github.com/i2mint/py2http
Author: Otosense
License: MIT
Keywords: http service,web service
Platform: any
License-File: LICENSE
Requires-Dist: bottle
Requires-Dist: PyJWT[crypto]
Requires-Dist: aiohttp
Requires-Dist: i2
Requires-Dist: glom
Requires-Dist: gunicorn
Requires-Dist: requests
Requires-Dist: strand
Requires-Dist: swagger-ui-py
Requires-Dist: pycparser
Requires-Dist: http2py
Provides-Extra: testing
Requires-Dist: http2py ; extra == 'testing'
